fast_censor/__init__.py
fast_censor/profanity_check_trie.py
fast_censor/wordlist_file_handler.py
fast_censor/word_lists/__init__.py
fast_censor/word_lists/clean_wordlist_decoded.txt
fast_censor/word_lists/clean_wordlist_encoded.txt
fast_censor/word_lists/locate.py
fast_censor/word_lists/profanity_wordlist_encoded.txt
fast_censor/word_lists/__pycache__/__init__.cpython-310.pyc
fast_censor/word_lists/__pycache__/__init__.cpython-39.pyc
fast_censor/word_lists/__pycache__/locate.cpython-310.pyc
fast_censor/word_lists/__pycache__/locate.cpython-39.pyc
fast_censor-0.3.2.dist-info/LICENSE
fast_censor-0.3.2.dist-info/METADATA
fast_censor-0.3.2.dist-info/WHEEL
fast_censor-0.3.2.dist-info/top_level.txt
fast_censor-0.3.2.dist-info/RECORD
