Metadata-Version: 2.2
Name: fast-censor
Version: 0.3.2
Summary: A fast and flexible utility for censoring and filtering text
Author: Matt Buchovecky
Author-email: mbuchove@gmail.com
Classifier: Programming Language :: Python :: 3
Classifier: License :: OSI Approved :: MIT License
License-File: LICENSE
Dynamic: author
Dynamic: author-email
Dynamic: classifier
Dynamic: description
Dynamic: description-content-type
Dynamic: summary
